{
  "users": [
    {
      "email": "akram@example.com",
      "password": "$2a$10$l0JicJY.TdagCQfdRhPRpehahF8gDJsMJzZbRGfOBQOSbsxNiWEn6",
      "name": "Akram",
      "id": 1
    },
    {
      "email": "akram@gmail.com",
      "password": "$2a$10$w44ktAuaHh6cKDXWQnnuGuObAuuuXiS.40v5nOuHqywTIQIc6F8su",
      "name": "Akram",
      "id": 2
    }
  ],
  "posts": [
    {
      "id": 1,
      "title": "Welcome to DevBlog",
      "description": "This is the first sample post in the application.",
      "image": "https://images.unsplash.com/photo-1499750310107-5fef28a66643",
      "authorId": 1,
      "authorName": "Akram",
      "createdAt": "2026-05-15T12:00:00Z"
    },
    {
      "title": "My First Real Post",
      "description": "Testing protected post creation.",
      "image": "https://images.unsplash.com/photo-1499750310107-5fef28a66643",
      "authorId": 1,
      "authorName": "Akram Gaber",
      "createdAt": "2026-05-15T12:00:00Z",
      "id": 2
    }
  ]
}